fastapi_tools/db/__init__.py
fastapi_tools/db/alembic.py
fastapi_tools/db/config.py
fastapi_tools/db/engine.py
fastapi_tools/db/entities.py
fastapi_tools/db/mixins.py
fastapi_tools/db/models.py
fastapi_tools/db/py.typed
fastapi_tools/db/types.py
fastapi_tools_db-0.2.6.dist-info/METADATA
fastapi_tools_db-0.2.6.dist-info/WHEEL
fastapi_tools_db-0.2.6.dist-info/RECORD
